risk/__init__.py
risk/risk.py
risk/annotation/__init__.py
risk/annotation/_nltk_setup.py
risk/annotation/annotation.py
risk/annotation/io.py
risk/cluster/__init__.py
risk/cluster/_community.py
risk/cluster/api.py
risk/cluster/cluster.py
risk/cluster/label.py
risk/log/__init__.py
risk/log/console.py
risk/log/parameters.py
risk/network/__init__.py
risk/network/io.py
risk/network/graph/__init__.py
risk/network/graph/_stats.py
risk/network/graph/_summary.py
risk/network/graph/api.py
risk/network/graph/graph.py
risk/network/plotter/__init__.py
risk/network/plotter/_canvas.py
risk/network/plotter/_contour.py
risk/network/plotter/_labels.py
risk/network/plotter/_network.py
risk/network/plotter/_plotter.py
risk/network/plotter/api.py
risk/network/plotter/_utils/__init__.py
risk/network/plotter/_utils/colors.py
risk/network/plotter/_utils/layout.py
risk/stats/__init__.py
risk/stats/api.py
risk/stats/_stats/__init__.py
risk/stats/_stats/tests.py
risk/stats/_stats/permutation/__init__.py
risk/stats/_stats/permutation/_test_functions.py
risk/stats/_stats/permutation/permutation.py
risk_network-0.1.1.dist-info/licenses/LICENSE
risk_network-0.1.1.dist-info/METADATA
risk_network-0.1.1.dist-info/WHEEL
risk_network-0.1.1.dist-info/top_level.txt
risk_network-0.1.1.dist-info/RECORD
