Metadata-Version: 2.4
Name: risk-network
Version: 0.1.1
Summary: A Python package for scalable network analysis and high-quality visualization.
Author-email: Ira Horecka <ira89@icloud.com>
License: GPL-3.0-or-later
Project-URL: Homepage, https://github.com/riskportal/risk
Project-URL: Issues, https://github.com/riskportal/risk/issues
Classifier: Development Status :: 4 - Beta
Classifier: Intended Audience :: Developers
Classifier: Intended Audience :: Science/Research
Classifier: License :: OSI Approved :: GNU General Public License v3 or later (GPLv3+)
Classifier: Operating System :: OS Independent
Classifier: Programming Language :: Python :: 3
Classifier: Programming Language :: Python :: 3.8
Classifier: Programming Language :: Python :: 3 :: Only
Classifier: Topic :: Scientific/Engineering :: Bio-Informatics
Classifier: Topic :: Scientific/Engineering :: Information Analysis
Classifier: Topic :: Scientific/Engineering :: Visualization
Classifier: Topic :: Software Development :: Libraries :: Python Modules
Requires-Python: >=3.8
License-File: LICENSE
Requires-Dist: ipywidgets
Requires-Dist: leidenalg
Requires-Dist: markov_clustering
Requires-Dist: matplotlib
Requires-Dist: networkx
Requires-Dist: nltk
Requires-Dist: numpy
Requires-Dist: openpyxl
Requires-Dist: pandas
Requires-Dist: python-igraph
Requires-Dist: python-louvain
Requires-Dist: scikit-learn
Requires-Dist: scipy
Requires-Dist: statsmodels
Requires-Dist: threadpoolctl
Requires-Dist: tqdm
Dynamic: license-file
